[
  {
    "type": "multiple-choice",
    "text": "أي من مبادئ بيان الأسلوب الرشيق التالية هي الأكثر ارتباطًا بتمكين الفريق؟",
    "explanation": "نظرًا لأن فريق التطوير يعد عاملًا مهمًا، فإن الأساليب الرشيقة تعزز الفرق الممكنة. يعمل الأفراد بشكل أفضل عندما يتم منحهم الاستقلالية لتنظيم وتخطيط عملهم الخاص. تدعو الأساليب الرشيقة إلى تحرير الفريق من الإدارة التفصيلية.",
    "choices": [
      {
        "text": "الطريقة الأكثر كفاءة وفعالية لتوصيل المعلومات إلى فريق التطوير وبداخله هي المحادثة المباشرة.",
        "correct": false
      },
      {
        "text": "عليك بإنشاء مشروعات حول الأفراد المحفزين. إعطائهم البيئة و الدعم الذي يحتاجونه و الوثوق بهم لإنجاز المهمة.",
        "correct": true
      },
      {
        "text": "البرمجيات الفعالة هي المقياس الرئيسي للتقدم.",
        "correct": false
      },
      {
        "text": "تدعم عمليات الأسلوب الرشيق Agile التطوير المستدام بحيث يجب أن يكون الراعي و المطورين و المستخدمين قادرين على الحفاظ على خطوة منتظمة دون أجل محدد.",
        "correct": false
      }
    ],
    "id": 1528
  },
  {
    "type": "multiple-choice",
    "text": "ينص المبدأ الثامن لبيان الأسلوب الرشيق على أن: “تدعم عمليات الأسلوب الرشيق Agile التطوير المستدام. يجب أن يكون الراعي و المطورون و المستخدمون قادرين على الحفاظ على وتيرة ثابتة إلى أجل غير مسمى.” أي من الممارسات والتقنيات الرشيقة التالية ترتبط ارتباطاً وثيقاً بهذا المبدأ؟",
    "explanation": "تدرك الأساليب الرشيقة قيمة الوتيرة المستدامة التي تسمح لأعضاء الفريق بالحفاظ على التوازن بين العمل والحياة. إن السماح للفريق بإنشاء ميثاق فريق خاص به مع معايير وقيم الفريق سيساعد في خلق بيئة رشيقة حيث يمكن لأعضاء الفريق العمل بأفضل ما لديهم من قدرات كفريق.",
    "choices": [
      {
        "text": "تحسين سجل الأعمال",
        "correct": false
      },
      {
        "text": "التكامل المستمر",
        "correct": false
      },
      {
        "text": "ميثاق الفريق",
        "correct": true
      },
      {
        "text": "التخطيط للتكرار",
        "correct": false
      }
    ],
    "id": 1529
  },
  {
    "type": "multiple-choice",
    "text": "يطلب الراعي من المطورين في فريق إسكرام إضافة عنصر مهم للغاية إلى الإطلاق الحالي. ماذا يجب أن يفعلوا؟",
    "explanation": "يجب على الفريق إبلاغ مالك المنتج أولاً لأنه مسؤول عن تحديد أولويات العناصر في سجل الأعمال.",
    "choices": [
      {
        "text": "إضافة العنصر إلى الإطلاق التالي.",
        "correct": false
      },
      {
        "text": "إبلاغ الأعضاء الآخرين في فريق إسكرام حتى يتمكنوا من اتخاذ القرار.",
        "correct": true
      },
      {
        "text": "إضافة العنصر إلى الإطلاق الحالي.",
        "correct": false
      },
      {
        "text": "إلغاء الإطلاق الحالي والبدء في إطلاق جديد بما في ذلك هذا العنصر.",
        "correct": false
      }
    ],
    "id": 1530
  },
  {
    "type": "multiple-choice",
    "text": "ألبرت مدير لمشروع كبير لاستحداث تذاكر الكترونية للسكك الحديدية بدلاً من التذاكر الورقية. ألبرت يتم توجيهه عن طريق جيم وهو مدير مشروع من ذوي الخبرة. ألبرت يتناقش مع جيم حول المشروع أنه مشروع ضخم جداً وهو يحتاج إلى تفويض بعض الأعمال إلى متخصصين. نصحه جيم بتفويض بعض الأعمال إلى متخصصين ولكن المساءلة عن ______ لا يمكن تفويضها أو تحويلها.",
    "explanation": "المساءلة عن إدارة التكامل لا يمكن تفويضها أو تحويلها. و يعتبر مدير المشروع هو من يجمح النتائج في جميع المجالات المعرفية الأخرى و لديه نظرة شاملة للمشروع",
    "choices": [
      {
        "text": "إدارة الجدول الزمني",
        "correct": false
      },
      {
        "text": "إدارة المشتريات",
        "correct": false
      },
      {
        "text": "إدارة التكامل",
        "correct": true
      },
      {
        "text": "إدارة الجودة",
        "correct": false
      }
    ],
    "id": 1531
  },
  {
    "type": "multiple-choice",
    "text": "انضم دييغو إلى مشروع إنشاءات كقائد فريق تصميم بدلاً من روبيرتو الذي استقال من المؤسسة. وقد اكتملت بالكامل خطة إدارة المشروع، و يقوم فريق المشروع حالياً بتنفيذ أعمال المشروع. دييغو يريد أن يعرف أدوار ومسؤوليات أعضاء فريقه بالتفصيل. أي من الأساليب التالية يستخدم لتقديم وصف تفصيلي لمسؤوليات أعضاء الفريق؟",
    "explanation": "يمكن تحديد مسؤوليات أعضاء الفريق التي تتطلب أوصاف مفصلة في أشكال قائمة على النص.",
    "choices": [
      {
        "text": "هيكل تجزئة الموارد",
        "correct": false
      },
      {
        "text": "مصفوفة تعيين المسؤوليات",
        "correct": false
      },
      {
        "text": "مخطط RACI",
        "correct": false
      },
      {
        "text": "أشكال قائمة على النص",
        "correct": true
      }
    ],
    "id": 1532
  },
  {
    "type": "multiple-choice",
    "text": "في منتصف الطريق أثناء الإطلاق، يقرر أحد المطورين أن فريق إسكرام أنه لن يكون قادراً على إكمال العناصر في سجل أعمال الإطلاق. من الذي يجب أن يكون حاضراً لمراجعة وتعديل سجل أعمال المنتج وفقاً لذلك؟",
    "explanation": "أثناء الإطلاق، يمكن توضيح النطاق وإعادة التفاوض بين مالك المنتج والمطورين عند اكتشاف المزيد.",
    "choices": [
      {
        "text": "مالك المنتج",
        "correct": false
      },
      {
        "text": "المطورين",
        "correct": false
      },
      {
        "text": "فريق إسكرام",
        "correct": false
      },
      {
        "text": "مالك المنتج و المطورين",
        "correct": true
      }
    ],
    "id": 1533
  },
  {
    "type": "multiple-choice",
    "text": "من الذي يجب أن يعرف أكثر عن التقدم نحو هدف الأعمال أو الإطلاق في فريق إسكرام؟",
    "explanation": "مالك المنتج مسؤول عن ترتيب أولويات العناصر في سجل أعمال المنتج وجعله مرئياً وشفافاً لجميع المعنيين. لذلك ، فهو يعرف أكثر عن التقدم نحو أهداف العمل.",
    "choices": [
      {
        "text": "راعي المشروع",
        "correct": false
      },
      {
        "text": "مدير إسكرام",
        "correct": false
      },
      {
        "text": "مالك المنتج",
        "correct": true
      },
      {
        "text": "المطورين",
        "correct": false
      }
    ],
    "id": 1534
  },
  {
    "type": "multiple-choice",
    "text": "في منتصف فترة التكرار، هناك تغيير مؤسسي كبير على وشك الحدوث وليس لدى أعضاء الفريق رؤية واضحة حول الاتجاه المستقبلي للمنتج. يشعر أعضاء الفريق أنه يجب وضع التكرار في حالة انتظار حتى يظهر المزيد من الوضوح حول مستقبل المنتج. من يجب أن يتخذ هذا القرار؟",
    "explanation": "مالك المنتج هو صاحب الصلاحية لإلغاء التكرار أو تعليقه.",
    "choices": [
      {
        "text": "مالك المنتج",
        "correct": true
      },
      {
        "text": "مدرب الفريق الرشيق",
        "correct": false
      },
      {
        "text": "الفريق",
        "correct": false
      },
      {
        "text": "راعي المشروع",
        "correct": false
      }
    ],
    "id": 1535
  },
  {
    "type": "multiple-choice",
    "text": "لقد لاحظ المدرب الرشيق أن الفريق يعمل ساعات إضافية لإكمال التكرار الحالي. أي مما يلي هو أفضل مسار للعمل؟",
    "explanation": "صحيحٌ أن الفريق يجب أن يحافظ على وتيرة ثابتة، ولهذا السبب يجب عليهم الالتزام فقط بما يمكنهم تقديمه وفقاً لتقديرات أحجام قصص المستخدمين وسرعة الفريق الإنتاجية.",
    "choices": [
      {
        "text": "يجب أن يلتزم الفريق بإكمال عدد أقل من القصص في التكرارات التالية.",
        "correct": true
      },
      {
        "text": "يجب إضافة موارد إضافية للحفاظ على وتيرة ثابتة.",
        "correct": false
      },
      {
        "text": "يجب على الفريق زيادة سرعته الإنتاجية.",
        "correct": false
      },
      {
        "text": "أعد حساب سرعة الفريق الإنتاجية وأعد بعض قصص المستخدمين إلى سجل أعمال المنتج.",
        "correct": false
      }
    ],
    "id": 1536
  },
  {
    "type": "multiple-choice",
    "text": "تنص القيمة الأولى لبيان الأسلوب الرشيق على ما يلي: “تقدر الفرق الرشيقة الأفراد والتفاعلات أكثر من العمليات والأدوات”. أي من الأساليب الرشيقة التالية تتوافق بشكل وثيق مع هذه القيمة لبيان الأسلوب الرشيق؟",
    "explanation": "بينما من المحتمل أن تكون العمليات والأدوات ضرورية في مشاريعنا، يجب أن نحاول تركيز انتباه الفريق على الأفراد والتفاعلات المعنية. هذا لأن المشاريع يتم تنفيذها من قبل الأشخاص وليس الأدوات، والمشاكل يتم حلها بواسطة الأشخاص وليس العمليات. وبالمثل، يتم قبول المشاريع من قبل الأشخاص، ويناقش النطاق عن طريق أشخاص، ويقبله أشخاص. لذلك من الضروري لنجاح المشاريع الرشيقة أن يكون لديك فرق ممكنة.",
    "choices": [
      {
        "text": "شاشة المعلومات",
        "correct": false
      },
      {
        "text": "تمكين الفريق",
        "correct": true
      },
      {
        "text": "فترة زمنية محددة",
        "correct": false
      },
      {
        "text": "إيقاع التسليم",
        "correct": false
      }
    ],
    "id": 1537
  },
  {
    "type": "multiple-choice",
    "text": "يناقش فريق المشروع أهداف التكرار التالي مع العميل ومالك المنتج، ثم يختارون قصص المستخدمين التي سيلتزمون بتقديمها كجزء من التكرار التالي. هذا السلوك يتوافق مع أي مبدأ من مبادئ بيان الأسلوب الرشيق؟",
    "explanation": "نظرًا لأن الفريق منظم ذاتياً ، سيكون من المهم للفريق مناقشة أهداف التكرار التالي مع العميل ثم تحديد قصص المستخدمين التي سيلتزمون بتقديمها كجزء من التكرار التالي. الفريق منظم ذاتياً ، ولا يمكن لمالك المنتج تحديد النقاط المهمة التالية من أعلى سجل الأعمال ثم إخبار الفريق بتنفيذ هذه الأعمال.",
    "choices": [
      {
        "text": "الأولوية القصوى لنا هي إرضاء العميل من خلال التسليم المبكر والمستمر للبرمجيات ذات القيمة.",
        "correct": false
      },
      {
        "text": "الترحيب بالمتطلبات المتغيرة، حتى لو كان في مرحلة متأخرة من التطوير. تعمل عمليات الأسلوب الرشيق على تسخير التغيير للمنفعة التنافسية للعميل.",
        "correct": false
      },
      {
        "text": "البساطة - فن تعظيم العمل غير المنجز - أمر أساسي.",
        "correct": false
      },
      {
        "text": "أفضل الهياكل و المتطلبات والتصميمات تنشأ من الفريق ذاتية التنظيم.",
        "correct": true
      }
    ],
    "id": 1538
  },
  {
    "type": "multiple-choice",
    "text": "في منتصف الطريق خلال المشروع ، ينشأ خلاف بين مدير المشروع وأحد أعضاء الفريق. يعتقد مدير المشروع أن أحد المهام يجب أن يتم تنفيذها من قبل عضو الفريق ، بينما عضو الفريق مقتنعًا بأنه ينبغي تنفيذها بواسطة شخص آخر. يقوم عضو الفريق بتصعيد الموقف إلى مديره الوظيفي. لحل النزاع ، يجب على مدير المشروع الرجوع الى _________.",
    "explanation": "تُعد مصفوفة RACI أداة مفيدة للاستخدام لضمان تخصيصات واضحة للأدوار والمسؤوليات حينما يتألف الفريق من موارد داخلية وخارجية.",
    "choices": [
      {
        "text": "تقويمات الموارد",
        "correct": false
      },
      {
        "text": "خطة إدارة الموارد",
        "correct": false
      },
      {
        "text": "هيكل تحليل الموارد",
        "correct": false
      },
      {
        "text": "مصفوفة RACI",
        "correct": true
      }
    ],
    "id": 1539
  },
  {
    "type": "multiple-choice",
    "text": "لقد تم تعيين صموئيل لتوه كمدير لمشروع اتصالات هاتفية بدلاً من غاري الذي إستقال مؤخراً من الشركة. المشروع كبير جدا و تبلغ ميزانيته 5000000 $. ويجري تنفيذ المشروع في مدينتين باستخدام 75 عضواً في الفريق. كانت هناك مشكلة فيما يتعلق بأنشطة الإختبار أن صموئيل لا يعرف من هو المسؤول عن تنفيذ هذه الأنشطة. ماذا يجب أن يفعل؟",
    "explanation": "مصفوفة تعيين المسؤوليات تبين موارد المشروع المخصصة لكل حزمة عمل. وتستخدم في توضيح العلاقات بين حزم العمل أو الأنشطة وأعضاء فريق المشروع",
    "choices": [
      {
        "text": "يجب عليه الرجوع إلى راعي المشروع لارشاده.",
        "correct": false
      },
      {
        "text": "يجب أن يجري إتصالاً بغاري يسأله عن دور كل واحد.",
        "correct": false
      },
      {
        "text": "يجب عليه مراجعة خطة إدارة الموارد.",
        "correct": false
      },
      {
        "text": "يجب عليه مراجعة مصفوفة تعيين المسؤوليات.",
        "correct": true
      }
    ],
    "id": 1540
  },
  {
    "type": "multiple-choice",
    "text": "ينص المبدأ الحادي عشر من بيان الأسلوب الرشيق على أن: \"أفضل الهياكل والمتطلبات والتصميمات تنشأ من فرق ذاتية التنظيم\". أي من الممارسات والتقنيات الرشيقة التالية ترتبط ارتباطاً وثيقاً بهذا المبدأ؟",
    "explanation": "تتمتع الفرق ذاتية التنظيم، التي تملك استقلالية اتخاذ القرارات المحلية، بمستوى أعلى من الشعور بالملكية والفخر تجاه البنيات والمتطلبات والتصاميم التي تبتكرها بنفسها، مقارنة بتلك التي تقترحها مصادر خارجية. ومعظم أعضاء الفريق الرشيق (Agile) هم 'متخصصون ذوو مهارات شمولية' (Generalizing Specialists)، أي أن لديهم تخصصاً رئيسياً واحداً، بالإضافة إلى خبرة واسعة تغطي مهارات متعددة.",
    "choices": [
      {
        "text": "تنقيح سجل الأعمال",
        "correct": false
      },
      {
        "text": "متخصصين متعددي المهارات",
        "correct": true
      },
      {
        "text": "العروض",
        "correct": false
      },
      {
        "text": "التكامل المستمر",
        "correct": false
      }
    ],
    "id": 1541
  },
  {
    "type": "multiple-choice",
    "text": "خلال أحد اجتماعات التقييم الرجعي، يناقش الفريق السرعة الإنتاجية المنخفضة للفريق أثناء التكرار الأخير. بعد التحقيق في السبب الجذري ، وجد أن السبب يرجع إلى عضو فريق مبتدئ ليس له خبرة كافية لإكمال قصص المستخدم التي تم إسنادها إليه في الوقت المقدر. ما هو أفضل مسار للعمل؟",
    "explanation": "وفقاً للقيمة الأولى لبيان الأسلوب الرشيق أننا نقدر الأفراد والتفاعلات أكثر من العمليات والأدوات، لن يكون من الجيد إستبدال عضو الفريق. سيكون من الأفضل إعطاء أولوية منخفضة ومهام سهلة له حتى يكتسب الخبرة المطلوبة.",
    "choices": [
      {
        "text": "قم بإسناد المهام ذات الأولوية المنخفضة أو المهام السهلة لعضو الفريق المبتدئ.",
        "correct": true
      },
      {
        "text": "قم بإستبدال عضو الفريق المبتدئ بآخر أكثر خبرة للحفاظ على السرعة الإنتاجية للفريق.",
        "correct": false
      },
      {
        "text": "قم بتقليل سرعة الفريق الإنتاجية للتكرارات القادمة حتى يكتسب عضو الفريق المبتدئ الخبرة المطلوبة.",
        "correct": false
      },
      {
        "text": "قم بتعيين عضو مبتدئ آخر في الفريق للحفاظ على سرعة الفريق.",
        "correct": false
      }
    ],
    "id": 1542
  }
]